Metadata-Version: 2.1
Name: radl
Version: 1.3.5
Summary: Resource and Application Description Language (RADL) parser.
Home-page: https://github.com/grycap/RADL
Author: GRyCAP - Universitat Politecnica de Valencia
Author-email: micafer1@upv.es
License: GPL version 3, http://www.gnu.org/licenses/gpl-3.0.txt
Platform: any
License-File: LICENSE
License-File: NOTICE
